<?xml version="1.0" encoding="UTF-8"?><items iblockUid="content:faq_s1" exchangeVersion="2"><item><field name="ACTIVE"><value>Y</value></field><field name="ACTIVE_FROM"><value>08.01.2024</value></field><field name="ACTIVE_TO"/><field name="SORT"><value>500</value></field><field name="NAME"><value>Как осуществить поверку?</value></field><field name="PREVIEW_PICTURE"/><field name="PREVIEW_TEXT"/><field name="PREVIEW_TEXT_TYPE"><value>text</value></field><field name="DETAIL_PICTURE"/><field name="DETAIL_TEXT"/><field name="DETAIL_TEXT_TYPE"><value>text</value></field><field name="CODE"/><field name="TAGS"/><field name="XML_ID"><value>788</value></field><field name="IBLOCK_SECTION"><value>Поверка счетчика|1|</value></field><property name="QUESTION"><value type="json">{&quot;TEXT&quot;:&quot;Как осуществить поверку?&quot;,&quot;TYPE&quot;:&quot;HTML&quot;}</value></property><property name="ANSWER"><value type="json">{&quot;TEXT&quot;:&quot;&lt;p&gt;\r\n\t Необходимо обратиться в&amp;nbsp;организацию, имеющую аккредитацию.\r\n&lt;\/p&gt;\r\n&lt;p&gt;\r\n\t &amp;nbsp;В Калининградской области поверку средств измерения, в т.ч. индивидуальных приборов учета проводят следующие аккредитованные организации:\r\n&lt;\/p&gt;\r\n&lt;p&gt;\r\n\t Федеральное бюджетное учреждение «Государственный региональный центр стандартизации, метрологии и испытаний в Калининградской области» (ФБУ «Калининградский ЦСМ»).\r\n&lt;\/p&gt;\r\n&lt;p&gt;\r\n\t Подать заявку и получить информацию можно через официальный сайт&amp;nbsp; &lt;a href=\&quot;https:\/\/39.csmrst.ru\/ru\&quot;&gt;https:\/\/39.csmrst.ru\/ru&lt;\/a&gt;&lt;a href=\&quot;https:\/\/39.csmrst.ru\/ru\&quot;&gt;&lt;\/a&gt;\r\n&lt;\/p&gt;\r\n&lt;p&gt;\r\n &lt;strong&gt;Государственное предприятие Калининградской области «Водоканал» (ГП КО «Водоканал».&lt;\/strong&gt;\r\n&lt;\/p&gt;\r\n&lt;p&gt;\r\n\t Подать заявку и получить информацию можно через официальный сайт &lt;a href=\&quot;https:\/\/www.vk39.ru\&quot;&gt;https:\/\/www.vk39.ru&lt;\/a&gt;\r\n&lt;\/p&gt;\r\n&lt;p&gt;\r\n\t Остерегайтесь мошенников!\r\n&lt;\/p&gt;&quot;,&quot;TYPE&quot;:&quot;HTML&quot;}</value></property><property name="VISIBLE"/></item><item><field name="ACTIVE"><value>Y</value></field><field name="ACTIVE_FROM"><value>08.01.2024</value></field><field name="ACTIVE_TO"/><field name="SORT"><value>500</value></field><field name="NAME"><value>Как узнать, когда делать поверку?</value></field><field name="PREVIEW_PICTURE"/><field name="PREVIEW_TEXT"/><field name="PREVIEW_TEXT_TYPE"><value>text</value></field><field name="DETAIL_PICTURE"/><field name="DETAIL_TEXT"/><field name="DETAIL_TEXT_TYPE"><value>text</value></field><field name="CODE"/><field name="TAGS"/><field name="XML_ID"><value>789</value></field><field name="IBLOCK_SECTION"><value>Поверка счетчика|1|</value></field><property name="QUESTION"><value type="json">{&quot;TEXT&quot;:&quot;Как узнать, когда делать поверку?&quot;,&quot;TYPE&quot;:&quot;HTML&quot;}</value></property><property name="ANSWER"><value type="json">{&quot;TEXT&quot;:&quot;&lt;p&gt;\r\n\t Срок поверки прибора учета указывается в паспорте (формуляре).\r\n&lt;\/p&gt;\r\n&lt;p&gt;\r\n\t В паспорте также указывается срок службы прибора. Не подлежат поверке счетчики, срок эксплуатации которых истек или они были признаны неисправными в результате механического повреждения.\r\n&lt;\/p&gt;\r\n&lt;p&gt;\r\n\t Также дата следующей поверки каждого счетчика указана в&amp;nbsp;ежемесячной квитанции за&amp;nbsp;коммунальные услуги.\r\n&lt;\/p&gt;&quot;,&quot;TYPE&quot;:&quot;HTML&quot;}</value></property><property name="VISIBLE"/></item><item><field name="ACTIVE"><value>Y</value></field><field name="ACTIVE_FROM"><value>08.01.2024</value></field><field name="ACTIVE_TO"/><field name="SORT"><value>500</value></field><field name="NAME"><value>Это обязательно?</value></field><field name="PREVIEW_PICTURE"/><field name="PREVIEW_TEXT"/><field name="PREVIEW_TEXT_TYPE"><value>text</value></field><field name="DETAIL_PICTURE"/><field name="DETAIL_TEXT"/><field name="DETAIL_TEXT_TYPE"><value>text</value></field><field name="CODE"/><field name="TAGS"/><field name="XML_ID"><value>790</value></field><field name="IBLOCK_SECTION"><value>Поверка счетчика|1|</value></field><property name="QUESTION"><value type="json">{&quot;TEXT&quot;:&quot;Это обязательно?&quot;,&quot;TYPE&quot;:&quot;HTML&quot;}</value></property><property name="ANSWER"><value type="json">{&quot;TEXT&quot;:&quot;&lt;p&gt;\r\n\t Да, проводить поверку требуется по&amp;nbsp;закону&amp;nbsp;—&amp;nbsp;&lt;a href=\&quot;http:\/\/www.consultant.ru\/document\/cons_doc_LAW_77904\/3bfb763ea01f7fc945dd7b589037fea5b6c90643\/\&quot; target=\&quot;_blank\&quot;&gt;ст. 13&amp;nbsp;Федерального закона от&amp;nbsp;26.06.2008&amp;nbsp;№&amp;nbsp;102-ФЗ&amp;nbsp;«Об&amp;nbsp;обеспечении единства измерений»&lt;\/a&gt;\r\n&lt;\/p&gt;&quot;,&quot;TYPE&quot;:&quot;HTML&quot;}</value></property><property name="VISIBLE"/></item><item><field name="ACTIVE"><value>Y</value></field><field name="ACTIVE_FROM"><value>08.01.2024</value></field><field name="ACTIVE_TO"/><field name="SORT"><value>500</value></field><field name="NAME"><value>Газоснабжение </value></field><field name="PREVIEW_PICTURE"/><field name="PREVIEW_TEXT"/><field name="PREVIEW_TEXT_TYPE"><value>text</value></field><field name="DETAIL_PICTURE"/><field name="DETAIL_TEXT"/><field name="DETAIL_TEXT_TYPE"><value>text</value></field><field name="CODE"/><field name="TAGS"/><field name="XML_ID"><value>791</value></field><field name="IBLOCK_SECTION"><value>Ресурсоснабжающие организации|1|</value></field><property name="QUESTION"><value type="json">{&quot;TEXT&quot;:&quot;Газоснабжение&quot;,&quot;TYPE&quot;:&quot;HTML&quot;}</value></property><property name="ANSWER"><value type="json">{&quot;TEXT&quot;:&quot;&lt;p&gt;\r\n\t ООО «Газпром межрегионгаз Санкт-Петербург»&amp;nbsp;\r\n&lt;\/p&gt;\r\n&lt;p&gt;\r\n\t г. Калининград, ул. Томская 22, тел. 8(4012)565 525,&amp;nbsp;&lt;a href=\&quot;https:\/\/www.peterburgregiongaz.ru\/\&quot;&gt;https:\/\/www.peterburgregiongaz.ru\/&lt;\/a&gt;\r\n&lt;\/p&gt;&quot;,&quot;TYPE&quot;:&quot;HTML&quot;}</value></property><property name="VISIBLE"/></item><item><field name="ACTIVE"><value>Y</value></field><field name="ACTIVE_FROM"><value>08.01.2024</value></field><field name="ACTIVE_TO"/><field name="SORT"><value>500</value></field><field name="NAME"><value>Холодное водоснабжение и (или) водоотведение </value></field><field name="PREVIEW_PICTURE"/><field name="PREVIEW_TEXT"/><field name="PREVIEW_TEXT_TYPE"><value>text</value></field><field name="DETAIL_PICTURE"/><field name="DETAIL_TEXT"/><field name="DETAIL_TEXT_TYPE"><value>text</value></field><field name="CODE"/><field name="TAGS"/><field name="XML_ID"><value>792</value></field><field name="IBLOCK_SECTION"><value>Ресурсоснабжающие организации|1|</value></field><property name="QUESTION"><value type="json">{&quot;TEXT&quot;:&quot;Холодное водоснабжение и (или) водоотведение&quot;,&quot;TYPE&quot;:&quot;HTML&quot;}</value></property><property name="ANSWER"><value type="json">{&quot;TEXT&quot;:&quot;&lt;p&gt;\r\n\t - ГП КО «Водоканал» г. Калининград, Советский пр-т, 107, тел. 8(4012) 555-151,&amp;nbsp;&lt;a href=\&quot;http:\/\/vk39.ru\/\&quot;&gt;http:\/\/vk39.ru\/&lt;\/a&gt;\r\n&lt;\/p&gt;\r\n&lt;p&gt;\r\n\t - МУП ЖКХ «Гурьевский водоканал» г. Гурьевск, ул. Лесная, 13, тел. 8(4012) 741-388 приёмная &lt;a href=\&quot;tel:+74012741647\&quot;&gt;8(4012) 741-647&lt;\/a&gt;&amp;nbsp;(диспетчерская)\r\n&lt;\/p&gt;&quot;,&quot;TYPE&quot;:&quot;HTML&quot;}</value></property><property name="VISIBLE"/></item><item><field name="ACTIVE"><value>Y</value></field><field name="ACTIVE_FROM"><value>08.01.2024</value></field><field name="ACTIVE_TO"/><field name="SORT"><value>500</value></field><field name="NAME"><value>Предоставление потребителям электрической энергии</value></field><field name="PREVIEW_PICTURE"/><field name="PREVIEW_TEXT"/><field name="PREVIEW_TEXT_TYPE"><value>text</value></field><field name="DETAIL_PICTURE"/><field name="DETAIL_TEXT"/><field name="DETAIL_TEXT_TYPE"><value>text</value></field><field name="CODE"/><field name="TAGS"/><field name="XML_ID"><value>793</value></field><field name="IBLOCK_SECTION"><value>Ресурсоснабжающие организации|1|</value></field><property name="QUESTION"><value type="json">{&quot;TEXT&quot;:&quot;Предоставление потребителям электрической энергии&quot;,&quot;TYPE&quot;:&quot;HTML&quot;}</value></property><property name="ANSWER"><value type="json">{&quot;TEXT&quot;:&quot;АО «Янтарьэнергосбыт»&amp;nbsp;&amp;nbsp;&amp;nbsp;&amp;nbsp;&amp;nbsp;&amp;nbsp;&amp;nbsp;&amp;nbsp;&amp;nbsp;&amp;nbsp;&amp;nbsp;&amp;nbsp;&amp;nbsp;&amp;nbsp;&amp;nbsp;&amp;nbsp;&amp;nbsp;&amp;nbsp;&amp;nbsp;&amp;nbsp;&amp;nbsp;&amp;nbsp;&amp;nbsp;&amp;nbsp;&amp;nbsp;&amp;nbsp;&amp;nbsp;&amp;nbsp;&amp;nbsp;&amp;nbsp;&amp;nbsp; г. Калининград,&amp;nbsp;ул. Дарвина, 10, тел. 8(4012) 605-885, 8(4012) 605-789, &amp;nbsp;&lt;a href=\&quot;https:\/\/yantarenergosbyt.ru\/\&quot;&gt;https:\/\/yantarenergosbyt.ru\/&lt;\/a&gt;&quot;,&quot;TYPE&quot;:&quot;HTML&quot;}</value></property><property name="VISIBLE"/></item><item><field name="ACTIVE"><value>Y</value></field><field name="ACTIVE_FROM"><value>08.01.2024</value></field><field name="ACTIVE_TO"/><field name="SORT"><value>500</value></field><field name="NAME"><value>Обращение с твердыми коммунальными отходами (ТКО)</value></field><field name="PREVIEW_PICTURE"/><field name="PREVIEW_TEXT"/><field name="PREVIEW_TEXT_TYPE"><value>text</value></field><field name="DETAIL_PICTURE"/><field name="DETAIL_TEXT"/><field name="DETAIL_TEXT_TYPE"><value>text</value></field><field name="CODE"/><field name="TAGS"/><field name="XML_ID"><value>794</value></field><field name="IBLOCK_SECTION"><value>Ресурсоснабжающие организации|1|</value></field><property name="QUESTION"><value type="json">{&quot;TEXT&quot;:&quot;Обращение с твердыми коммунальными отходами (ТКО)&quot;,&quot;TYPE&quot;:&quot;HTML&quot;}</value></property><property name="ANSWER"><value type="json">{&quot;TEXT&quot;:&quot;ГП КО «ЕСОО»&amp;nbsp;(Региональный оператор по вывозу мусора) ул. Озерная 33, тел.8(4012) 31-07-30,&amp;nbsp;&lt;a href=\&quot;https:\/\/esoo39.ru\/\&quot;&gt;https:\/\/esoo39.ru\/&lt;\/a&gt;&quot;,&quot;TYPE&quot;:&quot;HTML&quot;}</value></property><property name="VISIBLE"/></item><item><field name="ACTIVE"><value>Y</value></field><field name="ACTIVE_FROM"><value>08.01.2024</value></field><field name="ACTIVE_TO"/><field name="SORT"><value>500</value></field><field name="NAME"><value>Не нашли то, что искали?</value></field><field name="PREVIEW_PICTURE"/><field name="PREVIEW_TEXT"/><field name="PREVIEW_TEXT_TYPE"><value>text</value></field><field name="DETAIL_PICTURE"/><field name="DETAIL_TEXT"/><field name="DETAIL_TEXT_TYPE"><value>text</value></field><field name="CODE"/><field name="TAGS"/><field name="XML_ID"><value>795</value></field><field name="IBLOCK_SECTION"><value>Общие вопросы|1|</value></field><property name="QUESTION"><value type="json">{&quot;TEXT&quot;:&quot;Не нашли то, что искали?&quot;,&quot;TYPE&quot;:&quot;HTML&quot;}</value></property><property name="ANSWER"><value type="json">{&quot;TEXT&quot;:&quot;С радостью ответим на ваш вопрос&amp;nbsp;&lt;br&gt;\r\n по телефону единого контактного центра КТСХ-Сервис&amp;nbsp;&lt;br&gt;\r\n &lt;a href=\&quot;tel:74012973151\&quot;&gt;+7 (4012) 973 151&lt;\/a&gt;&amp;nbsp;&lt;br&gt;&quot;,&quot;TYPE&quot;:&quot;HTML&quot;}</value></property><property name="VISIBLE"><value>Y</value></property></item></items>